gitigno/__init__.py
gitigno/__main__.py
gitigno/constants.py
gitigno/core.py
gitigno/test.py
gitigno/utils.py
gitigno-0.0.3.dist-info/LICENSE.txt
gitigno-0.0.3.dist-info/METADATA
gitigno-0.0.3.dist-info/WHEEL
gitigno-0.0.3.dist-info/top_level.txt
gitigno-0.0.3.dist-info/RECORD
