Metadata-Version: 2.1
Name: gitigno
Version: 0.0.3
Summary: A Python CLI tool that generates a .gitignore template file using the gitignore.io API
Home-page: https://github.com/Minenhle-Ngubane/gitigno
Author: Minenhle Ngubane
Author-email: mino@minenhlengubane.com
License: MIT
Classifier: Programming Language :: Python :: 3.10
Classifier: License :: OSI Approved :: MIT License
Classifier: Operating System :: OS Independent
Requires-Python: >=3.10
License-File: LICENSE.txt
Requires-Dist: click (>=8.1.3)
Requires-Dist: requests (>=2.31.0)
Provides-Extra: dev
Requires-Dist: pytest (>=7.4.0) ; extra == 'dev'
Requires-Dist: twine (>=4.0.2) ; extra == 'dev'
